sparkplus/__init__.py
sparkplus/core/__init__.py
sparkplus/core/address_dataframe.py
sparkplus/core/base.py
sparkplus/core/coord_dataframe.py
sparkplus/core/job.py
sparkplus/core/numaddr_dataframe.py
sparkplus/core/py_log.py
sparkplus/core/roadname_dataframe.py
sparkplus/core/shp_to_parquet.py
sparkplus/core/tablename.py
sparkplus/core/udfs.py
sparkplus/core/utils.py
sparkplus/dependencies/__init__.py
sparkplus/dependencies/logging.py
sparkplus/dependencies/spark.py
sparkplus/dependencies/tablename.py
sparkplus/jobs/__init__.py
sparkplus/jobs/conversion.py
sparkplus/jobs/etl_job.py
sparkplus/jobs/load_database.py
sparkplus/jobs/table_to_df.py
sparkplus/jobs/with_geopandas.py
sparkplus/package/__init__.py
sparkplus/package/gis.py
sparkplus/package/pipeline.py
sparkplus-1.3.0.dist-info/LICENSE
sparkplus-1.3.0.dist-info/METADATA
sparkplus-1.3.0.dist-info/WHEEL
sparkplus-1.3.0.dist-info/top_level.txt
sparkplus-1.3.0.dist-info/RECORD
