Metadata-Version: 2.1
Name: sparkplus
Version: 1.3.0
Summary: GIS package for Apache Spark
Home-page: https://github.com/SWM-SparkPlus/sparkplus
Author: sparkplus
Author-email: meadea27@gmail.com
License: MIT
Keywords: spark,gis
Platform: UNKNOWN
Classifier: Programming Language :: Python :: 3
Classifier: License :: OSI Approved :: MIT License
Classifier: Operating System :: OS Independent
Requires-Python: >=3
License-File: LICENSE
Requires-Dist: numpy
Requires-Dist: pandas
Requires-Dist: geopandas
Requires-Dist: geospark
Requires-Dist: h3
Requires-Dist: geopy
Requires-Dist: pyarrow
Requires-Dist: rtree
Requires-Dist: shapely
Requires-Dist: python-dotenv
